{
    "chunk_id": "1/1",
    "status": 200,
    "headers": {
        "Date": "Fri, 20 Mar 2026 03:44:18 GMT",
        "Content-Type": "audio/mpeg",
        "Transfer-Encoding": "chunked",
        "Connection": "keep-alive",
        "content-security-policy": "default-src 'none'; frame-ancestors *; upgrade-insecure-requests",
        "access-control-allow-origin": "*",
        "access-control-allow-credentials": "true",
        "access-control-expose-headers": "*",
        "Cache-Control": "no-store, no-cache, private, must-revalidate",
        "cdn-cache-control": "no-store",
        "x-venice-version": "outerface-api-server-us-east1-02405-wl9",
        "x-venice-balance-usd": "16.11368571",
        "x-ratelimit-limit-requests": "60",
        "x-ratelimit-remaining-requests": "57",
        "x-ratelimit-reset-requests": "1773978315940",
        "x-ratelimit-resets": "1773978285920",
        "x-ratelimit-remaining": "20",
        "etag": "W/\"5df8d-oclKPpAyY2/g0JE7wbdgzQueu8M\"",
        "x-cloud-trace-context": "9e45bf96d144d49eaf630baeac7bfcfe",
        "Server": "cloudflare",
        "cf-cache-status": "DYNAMIC",
        "set-cookie": "_cfuvid=_pV123gSYX_FJAaPx3iFAOkfYXOUL0MleXk6meEEArA-1773978255.889009-1.0.1.1-hQ8iAOoz1lpw_gcXraaQn1W.R_Gqt9bt0nqNSlXBUi8; HttpOnly; SameSite=None; Secure; Path=/; Domain=venice.ai",
        "Strict-Transport-Security": "max-age=31536000; includeSubDomains; preload",
        "X-Content-Type-Options": "nosniff",
        "Referrer-Policy": "strict-origin",
        "X-Frame-Options": "SAMEORIGIN",
        "Permissions-Policy": "geolocation=(), camera=()",
        "Content-Encoding": "gzip",
        "CF-RAY": "9df1b7a34fbd01f2-DFW"
    },
    "elapsed_seconds": 2.3833377361297607,
    "error_text": null
}